COPYRIGHT.txt
LICENSE.txt
README.rst
setup.py
src/SSHLibrary/__init__.py
src/SSHLibrary/abstractclient.py
src/SSHLibrary/client.py
src/SSHLibrary/config.py
src/SSHLibrary/deco.py
src/SSHLibrary/javaclient.py
src/SSHLibrary/library.py
src/SSHLibrary/logger.py
src/SSHLibrary/pythonclient.py
src/SSHLibrary/pythonforward.py
src/SSHLibrary/sshconnectioncache.py
src/SSHLibrary/utils.py
src/SSHLibrary/version.py
src/robotframework_sshlibrary.egg-info/PKG-INFO
src/robotframework_sshlibrary.egg-info/SOURCES.txt
src/robotframework_sshlibrary.egg-info/dependency_links.txt
src/robotframework_sshlibrary.egg-info/requires.txt
src/robotframework_sshlibrary.egg-info/top_level.txt